VNE_SIM/SN.py
VNE_SIM/VNR.py
VNE_SIM/__init__.py
VNE_SIM/algorithm.py
VNE_SIM/simulation.py
VNE_SIM-2.76.dist-info/METADATA
VNE_SIM-2.76.dist-info/WHEEL
VNE_SIM-2.76.dist-info/top_level.txt
VNE_SIM-2.76.dist-info/RECORD
