Metadata-Version: 2.1
Name: VNE-SIM
Version: 2.76
Summary: virtual network embedding
Home-page: UNKNOWN
Author: tskui
Author-email: 158@qq.com
License: UNKNOWN
Platform: UNKNOWN
Classifier: Framework :: IPython
Classifier: Development Status :: 4 - Beta
Classifier: Topic :: Education :: Testing
Classifier: Operating System :: OS Independent
Classifier: License :: Public Domain
Classifier: Environment :: Win32 (MS Windows)
Classifier: Intended Audience :: Developers
Classifier: Programming Language :: Python
Classifier: Programming Language :: Python :: Implementation
Classifier: Programming Language :: Python :: 2
Classifier: Programming Language :: Python :: 2.7
Classifier: Programming Language :: Python :: 3
Classifier: Programming Language :: Python :: 3.4
Classifier: Programming Language :: Python :: 3.5
Classifier: Programming Language :: Python :: 3.6
Requires-Dist: numpy
Requires-Dist: networkx
Requires-Dist: scipy
Requires-Dist: xlwt
Requires-Dist: matplotlib
